soss/__init__.py
soss/__release__.py
soss/api/__init__.py
soss/api/api.py
soss/examples/__init__.py
soss/examples/bucket.py
soss/examples/multipart.py
soss/examples/object.py
soss/examples/service.py
soss/examples/test.doc.py
soss/utils/__init__.py
soss/utils/ossutils.py
soss/utils/xmlutils.py
soss-0.8.dist-info/DESCRIPTION.rst
soss-0.8.dist-info/METADATA
soss-0.8.dist-info/RECORD
soss-0.8.dist-info/WHEEL
soss-0.8.dist-info/metadata.json
soss-0.8.dist-info/top_level.txt
