Metadata-Version: 2.0
Name: soss
Version: 0.8
Summary: JRSS client for Python-3.x version.
Home-page: http://jr.jd.com
Author: Deyou Lee
Author-email: lideyou@jd.com
License: Apache Software License
Platform: UNKNOWN
Classifier: Development Status :: 5 - Production/Stable
Classifier: Intended Audience :: Developers
Classifier: Natural Language :: Chinese (Simplified)
Classifier: License :: OSI Approved :: Apache Software License
Classifier: Programming Language :: Python
Classifier: Programming Language :: Python :: 3
Classifier: Programming Language :: Python :: 3.4
Classifier: Programming Language :: Python :: 3.5
Classifier: Programming Language :: Python :: 3.6
Classifier: Programming Language :: Python :: Implementation :: PyPy
Classifier: Topic :: Software Development :: Libraries :: Python Modules
Requires-Python: >=3.4
Requires-Dist: xmltodict (>=0.11.0)
